docs/conf.py
docs/_build/html/_downloads/2db4d350e416e3adf54e890f00153125/convolution_2d.py
docs/examples/convolution_2d.py
examples/convolution_2d.py
pytorch_finufft/__init__.py
pytorch_finufft/checks.py
pytorch_finufft/functional.py
pytorch_finufft/py.typed
tests/conftest.py
tests/test_errors.py
tests/test_t1_backward.py
tests/test_t1_batch.py
tests/test_t1_forward.py
tests/test_t2_backward.py
tests/test_t2_batch.py
tests/test_t2_forward.py
pytorch_finufft-0.1.0.dist-info/LICENSE
pytorch_finufft-0.1.0.dist-info/METADATA
pytorch_finufft-0.1.0.dist-info/WHEEL
pytorch_finufft-0.1.0.dist-info/top_level.txt
pytorch_finufft-0.1.0.dist-info/RECORD
