Metadata-Version: 2.1
Name: pytorch_finufft
Version: 0.1.0
Summary: Pytorch bindings for the FINUFFT Library
Author-email: Matthew Meeker <mmeeker@flatironinstitute.org>, Michael Eickenberg <meickenberg@flatironinstitute.org>, Brian Ward <bward@flatironinstitute.org>
License: MIT
Project-URL: repository, https://github.com/flatironinstitute/pytorch-finufft
Project-URL: homepage, https://github.com/flatironinstitute/pytorch-finufft
Classifier: Development Status :: 3 - Alpha
Classifier: Intended Audience :: Developers
Classifier: Operating System :: OS Independent
Classifier: Topic :: Software Development :: Libraries :: Python Modules
Classifier: License :: OSI Approved :: MIT License
Classifier: Programming Language :: Python :: 3
Classifier: Programming Language :: Python :: 3.9
License-File: LICENSE
Requires-Dist: finufft >=2.2
Requires-Dist: torch >=2
Requires-Dist: numpy
Requires-Dist: scipy
Provides-Extra: cuda
Requires-Dist: cufinufft >=2.2.0 ; extra == 'cuda'
Provides-Extra: dev
Requires-Dist: black ; extra == 'dev'
Requires-Dist: mypy ; extra == 'dev'
Requires-Dist: isort ; extra == 'dev'
Requires-Dist: ruff ; extra == 'dev'
Requires-Dist: pytest ; extra == 'dev'
Requires-Dist: pytest-cov ; extra == 'dev'
